codes/__init__.py
codes/algorithm/__init__.py
codes/design/__init__.py
codes/design/singleton1.py
xmlclone_pdesign-0.0.7.dev4.dist-info/LICENSE
xmlclone_pdesign-0.0.7.dev4.dist-info/METADATA
xmlclone_pdesign-0.0.7.dev4.dist-info/WHEEL
xmlclone_pdesign-0.0.7.dev4.dist-info/top_level.txt
xmlclone_pdesign-0.0.7.dev4.dist-info/RECORD
