Metadata-Version: 2.1
Name: xmlclone-pdesign
Version: 0.0.7.dev4
Summary: My package description
Author-email: xmlclone <xmlclone@gmail.com>
License: MIT
Project-URL: Homepage, https://github.com/xmlclone/pdesign
Project-URL: Documentation, https://pdesign.readthedocs.io/en/latest
Project-URL: Code, https://github.com/xmlclone/pdesign
Project-URL: Help/Questions, https://github.com/xmlclone/pdesign
Project-URL: Issue tracker, https://github.com/xmlclone/pdesign
Classifier: Programming Language :: Python
Classifier: Programming Language :: Python :: 3
Requires-Python: >=3.7
License-File: LICENSE
